elara_wrapper/__init__.py
elara_wrapper/auth.py
elara_wrapper/interfaces.py
elara_wrapper/middleware.py
elara_wrapper-0.0.18.dist-info/METADATA
elara_wrapper-0.0.18.dist-info/WHEEL
elara_wrapper-0.0.18.dist-info/RECORD
