Metadata-Version: 2.3
Name: elara-wrapper
Version: 0.0.18
Summary: A FastAPI middleware package to validate requests to Elara agents based on the permissions set in their ENS name.
Requires-Python: >=3.11,<4.0
Classifier: Programming Language :: Python :: 3
Classifier: Programming Language :: Python :: 3.11
Classifier: Programming Language :: Python :: 3.12
Classifier: Programming Language :: Python :: 3.13
Requires-Dist: fastapi[standard] (>=0.115.14,<0.116.0)
Requires-Dist: libertai-agents (==0.2.0a1)
Requires-Dist: pydantic (>=2.11.7,<3.0.0)
Requires-Dist: web3 (>=7.12.0,<8.0.0)
